statesxt/.env.template
statesxt/.gitignore
statesxt/README.md
statesxt/__init__.py
statesxt/main.py
statesxt/named_ranges.py
statesxt/pyproject.toml
statesxt/pytest.ini
statesxt/restate.py
statesxt/results.json
statesxt/tox.ini
statesxt/.github/workflows/test.yml
statesxt/base/__init__.py
statesxt/base/base_driver.py
statesxt/base/check.py
statesxt/base/form.py
statesxt/base/mouse_keys.py
statesxt/base/table.py
statesxt/base/wait.py
statesxt/database/__init__.py
statesxt/database/database.py
statesxt/database/queries.py
statesxt/database/service.py
statesxt/database/mocks/mock_login_invalid.json
statesxt/database/mocks/mock_login_valid.json
statesxt/docs/Makefile
statesxt/docs/conf.py
statesxt/docs/index.rst
statesxt/docs/make.bat
statesxt/docs/requirements.txt
statesxt/docs/_static/css/custom.css
statesxt/docs/_static/images/structure-en.png
statesxt/docs/_static/images/uml-base.png
statesxt/docs/_static/images/uml-framework-states.png
statesxt/docs/_static/images/uml-framework.png
statesxt/docs/contents/README-md.rst
statesxt/docs/contents/base.rst
statesxt/docs/contents/database.rst
statesxt/docs/contents/env_template.rst
statesxt/docs/contents/gitignore.rst
statesxt/docs/contents/introduction.rst
statesxt/docs/contents/locators.rst
statesxt/docs/contents/pages.rst
statesxt/docs/contents/poetry-lock.rst
statesxt/docs/contents/pyproject-toml.rst
statesxt/docs/contents/pytest-ini.rst
statesxt/docs/contents/quick_start.rst
statesxt/docs/contents/testcases.rst
statesxt/docs/contents/utils.rst
statesxt/template/__init__.py
statesxt/template/interface.py
statesxt/template/locator.py
statesxt/template/page.py
statesxt/template/scenarios/__init__.py
statesxt/template/scenarios/test_0_1.py
statesxt/template/states/__init__.py
statesxt/template/states/states_0_1.py
statesxt/testcases/__init__.py
statesxt/testcases/conftest.py
statesxt/testcases/_fixtures/__init__.py
statesxt/testcases/_fixtures/auth.py
statesxt/testcases/_fixtures/composition.py
statesxt-0.5.13.dist-info/LICENSE
statesxt-0.5.13.dist-info/METADATA
statesxt-0.5.13.dist-info/WHEEL
statesxt-0.5.13.dist-info/entry_points.txt
statesxt-0.5.13.dist-info/top_level.txt
statesxt-0.5.13.dist-info/RECORD
