Metadata-Version: 2.1
Name: statesxt
Version: 0.5.13
Summary: A project template for testing your website application.
Home-page: https://test.pypi.org/project/statesxt/
Author: Jason Caleb
Author-email: cjsonnnnn@gmail.com
License: MIT License
Project-URL: Source, https://github.com/jsonnnnn/statesxt
Project-URL: Documentation, https://statesxt.readthedocs.io/en/latest/
Keywords: Selenium,Pytest,Python,project template,template,Testing,Framework
Classifier: Development Status :: 1 - Planning
Classifier: Framework :: Pytest
Classifier: Intended Audience :: Developers
Classifier: Operating System :: Microsoft :: Windows
Classifier: Programming Language :: Python
Classifier: Topic :: Software Development :: Testing
Classifier: Topic :: Utilities
Requires-Python: >=3.10
License-File: LICENSE
